notion_backup/backup_service.py
notion_backup/configuration_service.py
notion_backup/notion_client.py
notion_backup-0.3.9.dist-info/METADATA
notion_backup-0.3.9.dist-info/WHEEL
notion_backup-0.3.9.dist-info/entry_points.txt
notion_backup-0.3.9.dist-info/RECORD
